pyleiades/__init__.py
pyleiades/_version
pyleiades/energies.py
pyleiades/update.py
pyleiades/visuals.py
pyleiades/data/.DS_Store
pyleiades/data/EIA_MER.csv
pyleiades/data/EIA_MER_consumption.csv
pyleiades/data/EIA_MER_consumption.xlsx
pyleiades/data/EIA_MER_exports.csv
pyleiades/data/EIA_MER_exports.xlsx
pyleiades/data/EIA_MER_imports.csv
pyleiades/data/EIA_MER_imports.xlsx
pyleiades/data/EIA_MER_overview.csv
pyleiades/data/EIA_MER_overview.xlsx
pyleiades/data/EIA_MER_production.csv
pyleiades/data/EIA_MER_production.xlsx
pyleiades/data/.pytest_cache/.gitignore
pyleiades/data/.pytest_cache/CACHEDIR.TAG
pyleiades/data/.pytest_cache/README.md
pyleiades/data/.pytest_cache/v/cache/nodeids
pyleiades/data/.pytest_cache/v/cache/stepwise
pyleiades/data/archive/.DS_Store
pyleiades/data/archive/EIA_MER_20170628/EIA_MER_consumption.csv
pyleiades/data/archive/EIA_MER_20170628/EIA_MER_consumption.xlsx
pyleiades/data/archive/EIA_MER_20170628/EIA_MER_exports.csv
pyleiades/data/archive/EIA_MER_20170628/EIA_MER_exports.xlsx
pyleiades/data/archive/EIA_MER_20170628/EIA_MER_imports.csv
pyleiades/data/archive/EIA_MER_20170628/EIA_MER_imports.xlsx
pyleiades/data/archive/EIA_MER_20170628/EIA_MER_overview.csv
pyleiades/data/archive/EIA_MER_20170628/EIA_MER_overview.xlsx
pyleiades/data/archive/EIA_MER_20170628/EIA_MER_production.csv
pyleiades/data/archive/EIA_MER_20170628/EIA_MER_production.xlsx
pyleiades/data/archive/EIA_MER_20170726/.DS_Store
pyleiades/data/archive/EIA_MER_20170726/EIA_MER_consumption.csv
pyleiades/data/archive/EIA_MER_20170726/EIA_MER_consumption.xlsx
pyleiades/data/archive/EIA_MER_20170726/EIA_MER_exports.csv
pyleiades/data/archive/EIA_MER_20170726/EIA_MER_exports.xlsx
pyleiades/data/archive/EIA_MER_20170726/EIA_MER_imports.csv
pyleiades/data/archive/EIA_MER_20170726/EIA_MER_imports.xlsx
pyleiades/data/archive/EIA_MER_20170726/EIA_MER_overview.csv
pyleiades/data/archive/EIA_MER_20170726/EIA_MER_overview.xlsx
pyleiades/data/archive/EIA_MER_20170726/EIA_MER_production.csv
pyleiades-0.0.0.dev10.dist-info/LICENSE
pyleiades-0.0.0.dev10.dist-info/METADATA
pyleiades-0.0.0.dev10.dist-info/WHEEL
pyleiades-0.0.0.dev10.dist-info/top_level.txt
pyleiades-0.0.0.dev10.dist-info/RECORD
