Metadata-Version: 2.1
Name: pyleiades
Version: 0.0.0.dev10
Summary: An API for examing the EIA Monthly Energy Review datasets.
Home-page: https://github.com/mitchnegus/pyleiades
Author: Mitch Negus
Author-email: mitchell.negus.17@gmail.com
License: FreeBSD
Platform: UNKNOWN
